LICENSE
MANIFEST.in
README.md
setup.py
django_skrill.egg-info/PKG-INFO
django_skrill.egg-info/SOURCES.txt
django_skrill.egg-info/dependency_links.txt
django_skrill.egg-info/requires.txt
django_skrill.egg-info/top_level.txt
skrill/__init__.py
skrill/admin.py
skrill/models.py
skrill/settings.py
skrill/urls.py
skrill/views.py
skrill/migrations/0001_initial.py
skrill/migrations/0002_auto__add_field_paymentrequest_payment_methods.py
skrill/migrations/__init__.py
skrill/tests/__init__.py
skrill/tests/factories.py
skrill/tests/models_tests.py
skrill/tests/runtests.py
skrill/tests/urls.py
skrill/tests/views_tests.py