Metadata-Version: 1.0
Name: django-skrill
Version: 0.2.0
Summary: A reuseable Django application for integrating the Skrill (Moneybookers) payment API
Home-page: https://github.com/byteweaver/django-skrill
Author: byteweaver
Author-email: contact@byteweaver.net
License: Copyright (c) 2012, byteweaver
